{"code":0,"data":{"date":"2017-07-27","list":[{"baiduCoord":"125.31112257885152,43.902457855186725","baikeInfo":[],"content":"我妈排队买饼，买饼的都是女的。","contentText":"我妈排队买饼，买饼的都是女的。","createTime":"2017-07-27 18:18:17","eventTags":[],"favorCount":0,"hiddenContent":"","id":25161,"isBaikeInit":true,"isCoarseCoord":false,"isPublic":true,"latitude":43.89399321,"longitude":125.29821765,"mapCacheTime":"2021-05-23 14:49:36","mapUrlKey":"essay/25161/2021-05-23/map-2x.png","photos":[],"place":"早市","postTime":"2017-07-27 18:17:30","remarkId":null,"replyCount":0,"sourceModel":"小米手机5","sourceType":"Android客户端","timeZone":8,"eventTagsDetail":[]},{"baiduCoord":"","baikeInfo":[],"content":"我剪了头，然后等我妈剪头。她说她早上蹭到松树油了。","contentText":"我剪了头，然后等我妈剪头。她说她早上蹭到松树油了。","createTime":"2017-07-27 17:56:02","eventTags":[],"favorCount":0,"hiddenContent":"","id":25160,"isBaikeInit":true,"isCoarseCoord":true,"isPublic":true,"latitude":0,"longitude":0,"mapCacheTime":"","mapUrlKey":"","photos":[],"place":"理发店","postTime":"2017-07-27 17:55:28","remarkId":null,"replyCount":1,"sourceModel":"小米手机5","sourceType":"Android客户端","timeZone":8,"eventTagsDetail":[]},{"baiduCoord":"","baikeInfo":[],"content":"在拥挤的小路上前进真是费劲。","contentText":"在拥挤的小路上前进真是费劲。","createTime":"2017-07-27 14:17:57","eventTags":[],"favorCount":0,"hiddenContent":"","id":25159,"isBaikeInit":true,"isCoarseCoord":true,"isPublic":true,"latitude":0,"longitude":0,"mapCacheTime":"","mapUrlKey":"","photos":[],"place":"公交车","postTime":"2017-07-27 14:17:36","remarkId":null,"replyCount":0,"sourceModel":"小米手机5","sourceType":"Android客户端","timeZone":8,"eventTagsDetail":[]},{"baiduCoord":"","baikeInfo":[],"content":"那天听楠姐直播说二店没有一店大我就不想去二店了，还是去一店吧。","contentText":"那天听楠姐直播说二店没有一店大我就不想去二店了，还是去一店吧。","createTime":"2017-07-27 14:08:07","eventTags":[],"favorCount":0,"hiddenContent":"","id":25158,"isBaikeInit":true,"isCoarseCoord":true,"isPublic":true,"latitude":0,"longitude":0,"mapCacheTime":"","mapUrlKey":"","photos":[],"place":"站点","postTime":"2017-07-27 14:07:28","remarkId":null,"replyCount":0,"sourceModel":"小米手机5","sourceType":"Android客户端","timeZone":8,"eventTagsDetail":[]},{"baiduCoord":"125.31628217947537,43.90221617685237","baikeInfo":[],"content":"打算去小米之家瞅瞅昨天发布的手机。","contentText":"打算去小米之家瞅瞅昨天发布的手机。","createTime":"2017-07-27 14:06:23","eventTags":[],"favorCount":0,"hiddenContent":"","id":25157,"isBaikeInit":true,"isCoarseCoord":false,"isPublic":true,"latitude":43.89384275,"longitude":125.30333028,"mapCacheTime":"2021-05-23 14:49:36","mapUrlKey":"essay/25157/2021-05-23/map-2x.png","photos":[],"place":"站点","postTime":"2017-07-27 14:06:05","remarkId":null,"replyCount":0,"sourceModel":"小米手机5","sourceType":"Android客户端","timeZone":8,"eventTagsDetail":[]}],"total":5}}