{"code":0,"data":{"date":"2014-03-07","list":[{"baiduCoord":"","baikeInfo":[],"content":"贴吧新版客户端的字体变小了。。","contentText":"贴吧新版客户端的字体变小了。。","createTime":"2014-03-07 23:20:00","eventTags":[],"favorCount":0,"hiddenContent":"","id":4445,"isBaikeInit":true,"isCoarseCoord":true,"isPublic":true,"latitude":0,"longitude":0,"mapCacheTime":"","mapUrlKey":"","photos":[],"place":"","postTime":"2014-03-07 23:20:00","remarkId":null,"replyCount":0,"sourceModel":"","sourceType":"Android客户端","timeZone":8,"eventTagsDetail":[]},{"baiduCoord":"","baikeInfo":[],"content":"……今天的月亮好有意境","contentText":"……今天的月亮好有意境","createTime":"2014-03-07 23:04:00","eventTags":[],"favorCount":0,"hiddenContent":"","id":4444,"isBaikeInit":true,"isCoarseCoord":true,"isPublic":true,"latitude":0,"longitude":0,"mapCacheTime":"","mapUrlKey":"","photos":[],"place":"","postTime":"2014-03-07 23:04:00","remarkId":null,"replyCount":0,"sourceModel":"","sourceType":"Android客户端","timeZone":8,"eventTagsDetail":[]},{"baiduCoord":"","baikeInfo":[],"content":"路口这里围着一大圈施工","contentText":"路口这里围着一大圈施工","createTime":"2014-03-07 23:02:00","eventTags":[],"favorCount":0,"hiddenContent":"","id":4443,"isBaikeInit":true,"isCoarseCoord":true,"isPublic":true,"latitude":0,"longitude":0,"mapCacheTime":"","mapUrlKey":"","photos":[],"place":"","postTime":"2014-03-07 23:02:00","remarkId":null,"replyCount":0,"sourceModel":"","sourceType":"Android客户端","timeZone":8,"eventTagsDetail":[]},{"baiduCoord":"","baikeInfo":[],"content":"……在人民大街闯了一个黄灯","contentText":"……在人民大街闯了一个黄灯","createTime":"2014-03-07 22:58:00","eventTags":[],"favorCount":0,"hiddenContent":"","id":4442,"isBaikeInit":true,"isCoarseCoord":true,"isPublic":true,"latitude":0,"longitude":0,"mapCacheTime":"","mapUrlKey":"","photos":[],"place":"出租车","postTime":"2014-03-07 22:58:00","remarkId":null,"replyCount":0,"sourceModel":"","sourceType":"Android客户端","timeZone":8,"eventTagsDetail":[]},{"baiduCoord":"","baikeInfo":[],"content":"前面有一辆无照轿车","contentText":"前面有一辆无照轿车","createTime":"2014-03-07 22:56:00","eventTags":[],"favorCount":0,"hiddenContent":"","id":4441,"isBaikeInit":true,"isCoarseCoord":true,"isPublic":true,"latitude":0,"longitude":0,"mapCacheTime":"","mapUrlKey":"","photos":[],"place":"出租车","postTime":"2014-03-07 22:56:00","remarkId":null,"replyCount":0,"sourceModel":"","sourceType":"Android客户端","timeZone":8,"eventTagsDetail":[]},{"baiduCoord":"","baikeInfo":[{"id":70,"word":"刘济玮"}],"content":"对了昨天大晚居然没家长来，今天是刘济玮。","contentText":"对了昨天大晚居然没家长来，今天是刘济玮。","createTime":"2014-03-07 22:53:00","eventTags":[],"favorCount":0,"hiddenContent":"","id":4440,"isBaikeInit":true,"isCoarseCoord":true,"isPublic":true,"latitude":0,"longitude":0,"mapCacheTime":"","mapUrlKey":"","photos":[],"place":"出租车","postTime":"2014-03-07 22:53:00","remarkId":null,"replyCount":0,"sourceModel":"","sourceType":"Android客户端","timeZone":8,"eventTagsDetail":[]},{"baiduCoord":"","baikeInfo":[],"content":"芳，……","contentText":"芳，……","createTime":"2014-03-07 20:58:00","eventTags":[],"favorCount":0,"hiddenContent":"","id":4439,"isBaikeInit":false,"isCoarseCoord":true,"isPublic":false,"latitude":0,"longitude":0,"mapCacheTime":"","mapUrlKey":"","photos":[],"place":"班级","postTime":"2014-03-07 20:58:00","remarkId":null,"replyCount":0,"sourceModel":"","sourceType":"Android客户端","timeZone":8,"eventTagsDetail":[]},{"baiduCoord":"","baikeInfo":[],"content":"想和你永远在一起，那有多好……#王芳#","contentText":"想和你永远在一起，那有多好……","createTime":"2014-03-07 20:53:00","eventTags":[],"favorCount":0,"hiddenContent":"王芳","id":4438,"isBaikeInit":false,"isCoarseCoord":true,"isPublic":false,"latitude":0,"longitude":0,"mapCacheTime":"","mapUrlKey":"","photos":[],"place":"楼梯口","postTime":"2014-03-07 20:53:00","remarkId":null,"replyCount":0,"sourceModel":"","sourceType":"Android客户端","timeZone":8,"eventTagsDetail":[]},{"baiduCoord":"","baikeInfo":[],"content":"尼玛，作文一节课才憋出个标题……","contentText":"尼玛，作文一节课才憋出个标题……","createTime":"2014-03-07 20:49:00","eventTags":[],"favorCount":0,"hiddenContent":"","id":4437,"isBaikeInit":true,"isCoarseCoord":true,"isPublic":true,"latitude":0,"longitude":0,"mapCacheTime":"","mapUrlKey":"","photos":[],"place":"班级","postTime":"2014-03-07 20:49:00","remarkId":null,"replyCount":0,"sourceModel":"","sourceType":"Android客户端","timeZone":8,"eventTagsDetail":[]},{"baiduCoord":"","baikeInfo":[{"id":3,"word":"王芳"}],"content":"出去上厕所，又看见王芳了，偶合定律发生了啊……","contentText":"出去上厕所，又看见王芳了，偶合定律发生了啊……","createTime":"2014-03-07 19:04:00","eventTags":[],"favorCount":0,"hiddenContent":"","id":4436,"isBaikeInit":true,"isCoarseCoord":true,"isPublic":true,"latitude":0,"longitude":0,"mapCacheTime":"","mapUrlKey":"","photos":[],"place":"班级","postTime":"2014-03-07 19:04:00","remarkId":null,"replyCount":0,"sourceModel":"","sourceType":"Android客户端","timeZone":8,"eventTagsDetail":[]},{"baiduCoord":"","baikeInfo":[],"content":"土豆盖浇饭又咸又酸……难以下咽","contentText":"土豆盖浇饭又咸又酸……难以下咽","createTime":"2014-03-07 18:47:00","eventTags":[],"favorCount":0,"hiddenContent":"","id":4435,"isBaikeInit":true,"isCoarseCoord":true,"isPublic":true,"latitude":0,"longitude":0,"mapCacheTime":"","mapUrlKey":"","photos":[],"place":"前食堂","postTime":"2014-03-07 18:47:00","remarkId":null,"replyCount":0,"sourceModel":"","sourceType":"Android客户端","timeZone":8,"eventTagsDetail":[]},{"baiduCoord":"","baikeInfo":[{"id":3,"word":"王芳"}],"content":"刚刚下课我奔赴后食堂去看看有没有好吃的，结果发现后食堂还就平时那点东西一点都没意思，然后就想还像平常一样去前食堂吃饭，结果我跑到门口王芳恰好进来……现在我的左胳膊上还残留着芳香。","contentText":"刚刚下课我奔赴后食堂去看看有没有好吃的，结果发现后食堂还就平时那点东西一点都没意思，然后就想还像平常一样去前食堂吃饭，结果我跑到门口王芳恰好进来……现在我的左胳膊上还残留着芳香。","createTime":"2014-03-07 18:45:00","eventTags":[],"favorCount":0,"hiddenContent":"","id":4434,"isBaikeInit":true,"isCoarseCoord":true,"isPublic":true,"latitude":0,"longitude":0,"mapCacheTime":"","mapUrlKey":"","photos":[],"place":"前食堂","postTime":"2014-03-07 18:45:00","remarkId":null,"replyCount":0,"sourceModel":"","sourceType":"Android客户端","timeZone":8,"eventTagsDetail":[]},{"baiduCoord":"","baikeInfo":[],"content":"怎么如此的咸？","contentText":"怎么如此的咸？","createTime":"2014-03-07 18:40:00","eventTags":[],"favorCount":0,"hiddenContent":"","id":4433,"isBaikeInit":true,"isCoarseCoord":true,"isPublic":true,"latitude":0,"longitude":0,"mapCacheTime":"","mapUrlKey":"","photos":[],"place":"前食堂","postTime":"2014-03-07 18:40:00","remarkId":null,"replyCount":0,"sourceModel":"","sourceType":"Android客户端","timeZone":8,"eventTagsDetail":[]},{"baiduCoord":"","baikeInfo":[{"id":3,"word":"王芳"}],"content":"偶然间看见王芳从厕所出来回了四班","contentText":"偶然间看见王芳从厕所出来回了四班","createTime":"2014-03-07 16:01:00","eventTags":[],"favorCount":0,"hiddenContent":"","id":4432,"isBaikeInit":true,"isCoarseCoord":true,"isPublic":true,"latitude":0,"longitude":0,"mapCacheTime":"","mapUrlKey":"","photos":[],"place":"楼梯口","postTime":"2014-03-07 16:01:00","remarkId":null,"replyCount":0,"sourceModel":"","sourceType":"Android客户端","timeZone":8,"eventTagsDetail":[]},{"baiduCoord":"","baikeInfo":[{"id":3,"word":"王芳"}],"content":"王芳从一班的方向拿着一卷类似卫生纸的东西回了四班。","contentText":"王芳从一班的方向拿着一卷类似卫生纸的东西回了四班。","createTime":"2014-03-07 14:22:00","eventTags":[],"favorCount":0,"hiddenContent":"","id":4431,"isBaikeInit":true,"isCoarseCoord":true,"isPublic":true,"latitude":0,"longitude":0,"mapCacheTime":"","mapUrlKey":"","photos":[],"place":"班级","postTime":"2014-03-07 14:22:00","remarkId":null,"replyCount":0,"sourceModel":"","sourceType":"Android客户端","timeZone":8,"eventTagsDetail":[]},{"baiduCoord":"","baikeInfo":[],"content":"确实……为什么来前食堂吃饭的大多数都是男的","contentText":"确实……为什么来前食堂吃饭的大多数都是男的","createTime":"2014-03-07 12:02:00","eventTags":[],"favorCount":0,"hiddenContent":"","id":4430,"isBaikeInit":true,"isCoarseCoord":true,"isPublic":true,"latitude":0,"longitude":0,"mapCacheTime":"","mapUrlKey":"","photos":[],"place":"前食堂","postTime":"2014-03-07 12:02:00","remarkId":null,"replyCount":0,"sourceModel":"","sourceType":"Android客户端","timeZone":8,"eventTagsDetail":[]},{"baiduCoord":"","baikeInfo":[],"content":"上网卡那一张信号全无，看来是废了","contentText":"上网卡那一张信号全无，看来是废了","createTime":"2014-03-07 12:01:00","eventTags":[],"favorCount":0,"hiddenContent":"","id":4429,"isBaikeInit":true,"isCoarseCoord":true,"isPublic":true,"latitude":0,"longitude":0,"mapCacheTime":"","mapUrlKey":"","photos":[],"place":"前食堂","postTime":"2014-03-07 12:01:00","remarkId":null,"replyCount":0,"sourceModel":"","sourceType":"Android客户端","timeZone":8,"eventTagsDetail":[]},{"baiduCoord":"","baikeInfo":[{"id":26,"word":"张翔"}],"content":"没找到张翔","contentText":"没找到张翔","createTime":"2014-03-07 11:57:00","eventTags":[],"favorCount":0,"hiddenContent":"","id":4428,"isBaikeInit":true,"isCoarseCoord":true,"isPublic":true,"latitude":0,"longitude":0,"mapCacheTime":"","mapUrlKey":"","photos":[],"place":"前食堂","postTime":"2014-03-07 11:57:00","remarkId":null,"replyCount":0,"sourceModel":"","sourceType":"Android客户端","timeZone":8,"eventTagsDetail":[]},{"baiduCoord":"","baikeInfo":[],"content":"老师压了一分钟……","contentText":"老师压了一分钟……","createTime":"2014-03-07 11:49:00","eventTags":[],"favorCount":0,"hiddenContent":"","id":4427,"isBaikeInit":true,"isCoarseCoord":true,"isPublic":true,"latitude":0,"longitude":0,"mapCacheTime":"","mapUrlKey":"","photos":[],"place":"楼道","postTime":"2014-03-07 11:49:00","remarkId":null,"replyCount":0,"sourceModel":"","sourceType":"Android客户端","timeZone":8,"eventTagsDetail":[]},{"baiduCoord":"","baikeInfo":[{"id":3,"word":"王芳"}],"content":"去上厕所，没看见王芳。","contentText":"去上厕所，没看见王芳。","createTime":"2014-03-07 10:13:00","eventTags":[],"favorCount":0,"hiddenContent":"","id":4426,"isBaikeInit":true,"isCoarseCoord":true,"isPublic":true,"latitude":0,"longitude":0,"mapCacheTime":"","mapUrlKey":"","photos":[],"place":"班级","postTime":"2014-03-07 10:13:00","remarkId":null,"replyCount":0,"sourceModel":"","sourceType":"Android客户端","timeZone":8,"eventTagsDetail":[]},{"baiduCoord":"","baikeInfo":[],"content":"上节课物理课安老师没收了周岩的一堆电子产品，接着大家就发现老王正透过后面玻璃往里面瞅，不知道什么时候开始的。","contentText":"上节课物理课安老师没收了周岩的一堆电子产品，接着大家就发现老王正透过后面玻璃往里面瞅，不知道什么时候开始的。","createTime":"2014-03-07 10:13:00","eventTags":[],"favorCount":0,"hiddenContent":"","id":4425,"isBaikeInit":true,"isCoarseCoord":true,"isPublic":true,"latitude":0,"longitude":0,"mapCacheTime":"","mapUrlKey":"","photos":[],"place":"班级","postTime":"2014-03-07 10:13:00","remarkId":null,"replyCount":0,"sourceModel":"","sourceType":"Android客户端","timeZone":8,"eventTagsDetail":[]},{"baiduCoord":"","baikeInfo":[],"content":"这三个月，或许将是我人生中最艰难的三个月。","contentText":"这三个月，或许将是我人生中最艰难的三个月。","createTime":"2014-03-07 09:20:00","eventTags":[],"favorCount":0,"hiddenContent":"","id":4424,"isBaikeInit":true,"isCoarseCoord":true,"isPublic":true,"latitude":0,"longitude":0,"mapCacheTime":"","mapUrlKey":"","photos":[],"place":"班级","postTime":"2014-03-07 09:20:00","remarkId":null,"replyCount":0,"sourceModel":"","sourceType":"Android客户端","timeZone":8,"eventTagsDetail":[]},{"baiduCoord":"","baikeInfo":[],"content":"我认真做操更多的是想给别人一个引领，向别人证明我积极，我能行。","contentText":"我认真做操更多的是想给别人一个引领，向别人证明我积极，我能行。","createTime":"2014-03-07 09:18:00","eventTags":[],"favorCount":0,"hiddenContent":"","id":4423,"isBaikeInit":true,"isCoarseCoord":true,"isPublic":true,"latitude":0,"longitude":0,"mapCacheTime":"","mapUrlKey":"","photos":[],"place":"班级","postTime":"2014-03-07 09:18:00","remarkId":null,"replyCount":0,"sourceModel":"","sourceType":"Android客户端","timeZone":8,"eventTagsDetail":[]},{"baiduCoord":"","baikeInfo":[],"content":"孙天骁和王芳的第一件麻烦事……","contentText":"孙天骁和王芳的第一件麻烦事……","createTime":"2014-03-07 00:30:00","eventTags":[],"favorCount":0,"hiddenContent":"","id":4422,"isBaikeInit":false,"isCoarseCoord":true,"isPublic":false,"latitude":0,"longitude":0,"mapCacheTime":"","mapUrlKey":"","photos":[],"place":"","postTime":"2014-03-07 00:30:00","remarkId":null,"replyCount":0,"sourceModel":"","sourceType":"PC客户端","timeZone":8,"eventTagsDetail":[]}],"total":24}}