{"code":0,"data":{"date":"2022-08-10","list":[{"baiduCoord":"","baikeInfo":[{"id":318,"word":"圆点"}],"content":"把王女执剑记完成，陪圆点探索了下渊下宫。","contentText":"把王女执剑记完成，陪圆点探索了下渊下宫。","createTime":"2022-08-10 23:45:42","eventTags":[],"favorCount":0,"hiddenContent":"","id":58024,"isBaikeInit":true,"isCoarseCoord":false,"isPublic":false,"latitude":0,"longitude":0,"mapCacheTime":"","mapUrlKey":"","photos":[],"place":"公寓","postTime":"2022-08-10 23:45:43","remarkId":null,"replyCount":0,"sourceModel":"","sourceType":"网页客户端","timeZone":8,"eventTagsDetail":[]},{"baiduCoord":"","baikeInfo":[],"content":"在B站看了一个讲台湾战后史的系列，终于对台湾目前现状的行程原因有所了解。","contentText":"在B站看了一个讲台湾战后史的系列，终于对台湾目前现状的行程原因有所了解。","createTime":"2022-08-10 20:54:21","eventTags":[],"favorCount":0,"hiddenContent":"","id":58023,"isBaikeInit":true,"isCoarseCoord":false,"isPublic":true,"latitude":0,"longitude":0,"mapCacheTime":"","mapUrlKey":"","photos":[],"place":"公寓","postTime":"2022-08-10 20:54:21","remarkId":null,"replyCount":0,"sourceModel":"","sourceType":"网页客户端","timeZone":8,"eventTagsDetail":[]},{"baiduCoord":"114.5156526815998,30.49213478511764","baikeInfo":[{"id":306,"word":"林文韬"}],"content":"今天林文韬说北京来了领导给他们开会。","contentText":"今天林文韬说北京来了领导给他们开会。","createTime":"2022-08-10 19:12:36","eventTags":[],"favorCount":0,"hiddenContent":"","id":58022,"isBaikeInit":true,"isCoarseCoord":false,"isPublic":true,"latitude":30.48861991,"longitude":114.5038748,"mapCacheTime":"2022-08-10 19:12:37","mapUrlKey":"essay/58022/2022-08-10/map-2x-1660129957202.png","photos":[],"place":"武汉","postTime":"2022-08-10 19:12:16","remarkId":null,"replyCount":0,"sourceModel":"Xiaomi 12 Pro","sourceType":"Android客户端","timeZone":8,"eventTagsDetail":[]},{"baiduCoord":"114.51577853857547,30.49234580826094","baikeInfo":[],"content":"外面大排档一天比一天热闹。","contentText":"外面大排档一天比一天热闹。","createTime":"2022-08-10 19:12:12","eventTags":[],"favorCount":0,"hiddenContent":"","id":58021,"isBaikeInit":true,"isCoarseCoord":false,"isPublic":true,"latitude":30.48883339,"longitude":114.50400045,"mapCacheTime":"2022-08-10 19:12:14","mapUrlKey":"essay/58021/2022-08-10/map-2x-1660129934011.png","photos":[],"place":"武汉","postTime":"2022-08-10 19:12:03","remarkId":null,"replyCount":0,"sourceModel":"Xiaomi 12 Pro","sourceType":"Android客户端","timeZone":8,"eventTagsDetail":[]},{"baiduCoord":"114.51574589289035,30.492985128195265","baikeInfo":[],"content":"早睡呢，会胡思乱想。胡思乱想呢，就会失眠。所以不如晚点睡，让睡觉之前没力气想。","contentText":"早睡呢，会胡思乱想。胡思乱想呢，就会失眠。所以不如晚点睡，让睡觉之前没力气想。","createTime":"2022-08-10 19:11:31","eventTags":[],"favorCount":0,"hiddenContent":"","id":58020,"isBaikeInit":true,"isCoarseCoord":false,"isPublic":true,"latitude":30.48947166,"longitude":114.50396706,"mapCacheTime":"2022-08-10 19:11:33","mapUrlKey":"essay/58020/2022-08-10/map-2x-1660129893080.png","photos":[],"place":"武汉","postTime":"2022-08-10 19:10:50","remarkId":null,"replyCount":0,"sourceModel":"Xiaomi 12 Pro","sourceType":"Android客户端","timeZone":8,"eventTagsDetail":[]},{"baiduCoord":"","baikeInfo":[],"content":"突发奇想去搜智商测试，在费劲吧啦做完40道题之后，告诉我查看结果要支付9.99欧元。","contentText":"突发奇想去搜智商测试，在费劲吧啦做完40道题之后，告诉我查看结果要支付9.99欧元。","createTime":"2022-08-10 17:45:08","eventTags":[],"favorCount":0,"hiddenContent":"","id":58019,"isBaikeInit":true,"isCoarseCoord":false,"isPublic":true,"latitude":0,"longitude":0,"mapCacheTime":"","mapUrlKey":"","photos":[],"place":"公寓","postTime":"2022-08-10 17:45:09","remarkId":null,"replyCount":0,"sourceModel":"","sourceType":"网页客户端","timeZone":8,"eventTagsDetail":[]},{"baiduCoord":"","baikeInfo":[],"content":"React18 我现在确实没有什么了解啊。","contentText":"React18 我现在确实没有什么了解啊。","createTime":"2022-08-10 14:48:18","eventTags":[],"favorCount":0,"hiddenContent":"","id":58018,"isBaikeInit":true,"isCoarseCoord":false,"isPublic":true,"latitude":0,"longitude":0,"mapCacheTime":"","mapUrlKey":"","photos":[],"place":"公寓","postTime":"2022-08-10 14:48:18","remarkId":null,"replyCount":0,"sourceModel":"","sourceType":"网页客户端","timeZone":8,"eventTagsDetail":[]},{"baiduCoord":"","baikeInfo":[],"content":"面了一个试，不困了不困了。","contentText":"面了一个试，不困了不困了。","createTime":"2022-08-10 14:47:50","eventTags":[],"favorCount":0,"hiddenContent":"","id":58017,"isBaikeInit":true,"isCoarseCoord":false,"isPublic":true,"latitude":0,"longitude":0,"mapCacheTime":"","mapUrlKey":"","photos":[],"place":"公寓","postTime":"2022-08-10 14:47:51","remarkId":null,"replyCount":0,"sourceModel":"","sourceType":"网页客户端","timeZone":8,"eventTagsDetail":[]},{"baiduCoord":"","baikeInfo":[{"id":131,"word":"吕雨晴"}],"content":"我真的是，越想好好休息就越休息不好。吕雨晴写了一篇读后感，我一句话都看不进去。","contentText":"我真的是，越想好好休息就越休息不好。吕雨晴写了一篇读后感，我一句话都看不进去。","createTime":"2022-08-10 11:28:43","eventTags":[],"favorCount":0,"hiddenContent":"","id":58016,"isBaikeInit":true,"isCoarseCoord":false,"isPublic":true,"latitude":0,"longitude":0,"mapCacheTime":"","mapUrlKey":"","photos":[],"place":"公寓","postTime":"2022-08-10 11:27:37","remarkId":null,"replyCount":0,"sourceModel":"Xiaomi 12 Pro","sourceType":"Android客户端","timeZone":8,"eventTagsDetail":[]},{"baiduCoord":"","baikeInfo":[],"content":"又是一个没睡好的晚上。。","contentText":"又是一个没睡好的晚上。。","createTime":"2022-08-10 06:26:26","eventTags":[],"favorCount":0,"hiddenContent":"","id":58015,"isBaikeInit":true,"isCoarseCoord":false,"isPublic":true,"latitude":0,"longitude":0,"mapCacheTime":"","mapUrlKey":"","photos":[],"place":"公寓","postTime":"2022-08-10 06:26:18","remarkId":null,"replyCount":1,"sourceModel":"Xiaomi 12 Pro","sourceType":"Android客户端","timeZone":8,"eventTagsDetail":[]}],"total":10}}