{"code":0,"data":{"date":"2014-08-27","list":[{"baiduCoord":"","baikeInfo":[],"content":"刚才差点发重，幸好服务器挡住了，是我的客户端还有小瑕疵。。话说广播的音乐戛然而止了。。","contentText":"刚才差点发重，幸好服务器挡住了，是我的客户端还有小瑕疵。。话说广播的音乐戛然而止了。。","createTime":"2014-08-27 21:30:47","eventTags":[],"favorCount":0,"hiddenContent":"","id":7342,"isBaikeInit":true,"isCoarseCoord":true,"isPublic":true,"latitude":0,"longitude":0,"mapCacheTime":"","mapUrlKey":"","photos":[],"place":"火车","postTime":"2014-08-27 21:30:47","remarkId":null,"replyCount":0,"sourceModel":"","sourceType":"Android客户端","timeZone":8,"eventTagsDetail":[]},{"baiduCoord":"","baikeInfo":[],"content":"广播又开始播放“悠扬的乐曲”","contentText":"广播又开始播放“悠扬的乐曲”","createTime":"2014-08-27 21:28:30","eventTags":[],"favorCount":0,"hiddenContent":"","id":7341,"isBaikeInit":true,"isCoarseCoord":true,"isPublic":true,"latitude":0,"longitude":0,"mapCacheTime":"","mapUrlKey":"","photos":[],"place":"火车","postTime":"2014-08-27 21:28:30","remarkId":null,"replyCount":0,"sourceModel":"","sourceType":"Android客户端","timeZone":8,"eventTagsDetail":[]},{"baiduCoord":"","baikeInfo":[],"content":"现在开移动电源开始充电了","contentText":"现在开移动电源开始充电了","createTime":"2014-08-27 20:23:16","eventTags":[],"favorCount":0,"hiddenContent":"","id":7340,"isBaikeInit":true,"isCoarseCoord":true,"isPublic":true,"latitude":0,"longitude":0,"mapCacheTime":"","mapUrlKey":"","photos":[],"place":"火车","postTime":"2014-08-27 20:23:16","remarkId":null,"replyCount":0,"sourceModel":"","sourceType":"Android客户端","timeZone":8,"eventTagsDetail":[]},{"baiduCoord":"","baikeInfo":[],"content":"下站沈阳。","contentText":"下站沈阳。","createTime":"2014-08-27 20:22:01","eventTags":[],"favorCount":0,"hiddenContent":"","id":7339,"isBaikeInit":true,"isCoarseCoord":true,"isPublic":true,"latitude":0,"longitude":0,"mapCacheTime":"","mapUrlKey":"","photos":[],"place":"火车","postTime":"2014-08-27 20:22:01","remarkId":null,"replyCount":0,"sourceModel":"","sourceType":"Android客户端","timeZone":8,"eventTagsDetail":[]},{"baiduCoord":"","baikeInfo":[],"content":"这六个铺位就我、我爸和一个女的","contentText":"这六个铺位就我、我爸和一个女的","createTime":"2014-08-27 20:21:33","eventTags":[],"favorCount":0,"hiddenContent":"","id":7338,"isBaikeInit":true,"isCoarseCoord":true,"isPublic":true,"latitude":0,"longitude":0,"mapCacheTime":"","mapUrlKey":"","photos":[],"place":"火车","postTime":"2014-08-27 20:21:33","remarkId":null,"replyCount":0,"sourceModel":"","sourceType":"Android客户端","timeZone":8,"eventTagsDetail":[]},{"baiduCoord":"","baikeInfo":[],"content":"音乐已经停了，车厢也没几个人，很空","contentText":"音乐已经停了，车厢也没几个人，很空","createTime":"2014-08-27 20:20:57","eventTags":[],"favorCount":0,"hiddenContent":"","id":7337,"isBaikeInit":true,"isCoarseCoord":true,"isPublic":true,"latitude":0,"longitude":0,"mapCacheTime":"","mapUrlKey":"","photos":[],"place":"","postTime":"2014-08-27 20:20:57","remarkId":null,"replyCount":0,"sourceModel":"","sourceType":"Android客户端","timeZone":8,"eventTagsDetail":[]},{"baiduCoord":"","baikeInfo":[],"content":"到四平了","contentText":"到四平了","createTime":"2014-08-27 20:20:33","eventTags":[],"favorCount":0,"hiddenContent":"","id":7336,"isBaikeInit":true,"isCoarseCoord":true,"isPublic":true,"latitude":0,"longitude":0,"mapCacheTime":"","mapUrlKey":"","photos":[],"place":"","postTime":"2014-08-27 20:20:33","remarkId":null,"replyCount":0,"sourceModel":"","sourceType":"Android客户端","timeZone":8,"eventTagsDetail":[]},{"baiduCoord":"","baikeInfo":[],"content":"刚刚在网上搜了一下网络连接的问题，也没有搜到有用的信息。","contentText":"刚刚在网上搜了一下网络连接的问题，也没有搜到有用的信息。","createTime":"2014-08-27 20:03:18","eventTags":[],"favorCount":0,"hiddenContent":"","id":7335,"isBaikeInit":true,"isCoarseCoord":true,"isPublic":true,"latitude":0,"longitude":0,"mapCacheTime":"","mapUrlKey":"","photos":[],"place":"火车","postTime":"2014-08-27 20:03:18","remarkId":null,"replyCount":0,"sourceModel":"","sourceType":"Android客户端","timeZone":8,"eventTagsDetail":[]},{"baiduCoord":"","baikeInfo":[],"content":"不行啊，火车上获取不到GPS位置信息……再等等吧。","contentText":"不行啊，火车上获取不到GPS位置信息……再等等吧。","createTime":"2014-08-27 20:02:21","eventTags":[],"favorCount":0,"hiddenContent":"","id":7334,"isBaikeInit":true,"isCoarseCoord":true,"isPublic":true,"latitude":0,"longitude":0,"mapCacheTime":"","mapUrlKey":"","photos":[],"place":"火车","postTime":"2014-08-27 20:02:21","remarkId":null,"replyCount":0,"sourceModel":"","sourceType":"Android客户端","timeZone":8,"eventTagsDetail":[]},{"baiduCoord":"","baikeInfo":[],"content":"应该过了四平了吧。。","contentText":"应该过了四平了吧。。","createTime":"2014-08-27 20:01:27","eventTags":[],"favorCount":0,"hiddenContent":"","id":7333,"isBaikeInit":true,"isCoarseCoord":true,"isPublic":true,"latitude":0,"longitude":0,"mapCacheTime":"","mapUrlKey":"","photos":[],"place":"火车","postTime":"2014-08-27 20:01:27","remarkId":null,"replyCount":0,"sourceModel":"","sourceType":"Android客户端","timeZone":8,"eventTagsDetail":[]},{"baiduCoord":"","baikeInfo":[],"content":"我想，火车的金属顶，应该很挡GPS信号吧","contentText":"我想，火车的金属顶，应该很挡GPS信号吧","createTime":"2014-08-27 20:01:02","eventTags":[],"favorCount":0,"hiddenContent":"","id":7332,"isBaikeInit":true,"isCoarseCoord":true,"isPublic":true,"latitude":0,"longitude":0,"mapCacheTime":"","mapUrlKey":"","photos":[],"place":"火车","postTime":"2014-08-27 20:01:02","remarkId":null,"replyCount":0,"sourceModel":"","sourceType":"Android客户端","timeZone":8,"eventTagsDetail":[]},{"baiduCoord":"","baikeInfo":[],"content":"我在上铺躺着，GPS获取中","contentText":"我在上铺躺着，GPS获取中","createTime":"2014-08-27 20:00:13","eventTags":[],"favorCount":0,"hiddenContent":"","id":7331,"isBaikeInit":true,"isCoarseCoord":true,"isPublic":true,"latitude":0,"longitude":0,"mapCacheTime":"","mapUrlKey":"","photos":[],"place":"火车","postTime":"2014-08-27 20:00:13","remarkId":null,"replyCount":0,"sourceModel":"","sourceType":"Android客户端","timeZone":8,"eventTagsDetail":[]},{"baiduCoord":"","baikeInfo":[],"content":"火车上有个人播音乐很大声。","contentText":"火车上有个人播音乐很大声。","createTime":"2014-08-27 19:59:40","eventTags":[],"favorCount":0,"hiddenContent":"","id":7330,"isBaikeInit":true,"isCoarseCoord":true,"isPublic":true,"latitude":0,"longitude":0,"mapCacheTime":"","mapUrlKey":"","photos":[],"place":"火车","postTime":"2014-08-27 19:59:40","remarkId":null,"replyCount":0,"sourceModel":"","sourceType":"Android客户端","timeZone":8,"eventTagsDetail":[]},{"baiduCoord":"125.1591043981104,43.77663587493651","baikeInfo":[],"content":"应该快出长春了吧，长春南到了吗，外面黑看不到","contentText":"应该快出长春了吧，长春南到了吗，外面黑看不到","createTime":"2014-08-27 19:05:31","eventTags":[],"favorCount":0,"hiddenContent":"","id":7329,"isBaikeInit":true,"isCoarseCoord":false,"isPublic":true,"latitude":43.76776209,"longitude":125.14621001,"mapCacheTime":"2021-05-23 15:20:02","mapUrlKey":"essay/7329/2021-05-23/map-2x.png","photos":[],"place":"火车","postTime":"2014-08-27 19:05:31","remarkId":null,"replyCount":0,"sourceModel":"","sourceType":"Android客户端","timeZone":8,"eventTagsDetail":[]},{"baiduCoord":"125.17173014307127,43.78781443711086","baikeInfo":[],"content":"我爸在下铺躺着","contentText":"我爸在下铺躺着","createTime":"2014-08-27 19:04:41","eventTags":[],"favorCount":0,"hiddenContent":"","id":7328,"isBaikeInit":true,"isCoarseCoord":false,"isPublic":true,"latitude":43.77895485,"longitude":125.15886103,"mapCacheTime":"2021-05-23 15:20:02","mapUrlKey":"essay/7328/2021-05-23/map-2x.png","photos":[],"place":"火车","postTime":"2014-08-27 19:04:41","remarkId":null,"replyCount":0,"sourceModel":"","sourceType":"Android客户端","timeZone":8,"eventTagsDetail":[]},{"baiduCoord":"125.1762877853,43.79183337370842","baikeInfo":[],"content":"我在靠窗坐着","contentText":"我在靠窗坐着","createTime":"2014-08-27 19:04:23","eventTags":[],"favorCount":0,"hiddenContent":"","id":7327,"isBaikeInit":true,"isCoarseCoord":false,"isPublic":true,"latitude":43.78301803,"longitude":125.16341311,"mapCacheTime":"2021-05-23 15:20:02","mapUrlKey":"essay/7327/2021-05-23/map-2x.png","photos":[],"place":"火车","postTime":"2014-08-27 19:04:23","remarkId":null,"replyCount":0,"sourceModel":"","sourceType":"Android客户端","timeZone":8,"eventTagsDetail":[]},{"baiduCoord":"125.18675059249432,43.79970927747312","baikeInfo":[],"content":"我在这里","contentText":"我在这里","createTime":"2014-08-27 19:03:45","eventTags":[],"favorCount":0,"hiddenContent":"","id":7326,"isBaikeInit":true,"isCoarseCoord":false,"isPublic":true,"latitude":43.79105859,"longitude":125.1738413,"mapCacheTime":"2021-05-23 15:20:03","mapUrlKey":"essay/7326/2021-05-23/map-2x.png","photos":[],"place":"火车","postTime":"2014-08-27 19:03:45","remarkId":null,"replyCount":0,"sourceModel":"","sourceType":"Android客户端","timeZone":8,"eventTagsDetail":[]},{"baiduCoord":"","baikeInfo":[],"content":"我现在特别喜欢看到发布成功的提示","contentText":"我现在特别喜欢看到发布成功的提示","createTime":"2014-08-27 19:03:08","eventTags":[],"favorCount":0,"hiddenContent":"","id":7325,"isBaikeInit":true,"isCoarseCoord":true,"isPublic":true,"latitude":0,"longitude":0,"mapCacheTime":"","mapUrlKey":"","photos":[],"place":"火车","postTime":"2014-08-27 19:03:08","remarkId":null,"replyCount":0,"sourceModel":"","sourceType":"Android客户端","timeZone":8,"eventTagsDetail":[]},{"baiduCoord":"","baikeInfo":[],"content":"不行，必须解决下这个网络连接的问题，不然每次发随记都需要重启，怎么直播。。。","contentText":"不行，必须解决下这个网络连接的问题，不然每次发随记都需要重启，怎么直播。。。","createTime":"2014-08-27 19:02:43","eventTags":[],"favorCount":0,"hiddenContent":"","id":7324,"isBaikeInit":true,"isCoarseCoord":true,"isPublic":true,"latitude":0,"longitude":0,"mapCacheTime":"","mapUrlKey":"","photos":[],"place":"火车","postTime":"2014-08-27 19:02:43","remarkId":null,"replyCount":0,"sourceModel":"","sourceType":"Android客户端","timeZone":8,"eventTagsDetail":[]},{"baiduCoord":"","baikeInfo":[],"content":"现在在火车","contentText":"现在在火车","createTime":"2014-08-27 18:46:31","eventTags":[],"favorCount":0,"hiddenContent":"","id":7323,"isBaikeInit":false,"isCoarseCoord":true,"isPublic":false,"latitude":0,"longitude":0,"mapCacheTime":"","mapUrlKey":"","photos":[],"place":"火车","postTime":"2014-08-27 18:46:31","remarkId":null,"replyCount":0,"sourceModel":"","sourceType":"Android客户端","timeZone":8,"eventTagsDetail":[]},{"baiduCoord":"","baikeInfo":[],"content":"我已经上车了！","contentText":"我已经上车了！","createTime":"2014-08-27 18:46:21","eventTags":[],"favorCount":0,"hiddenContent":"","id":7322,"isBaikeInit":true,"isCoarseCoord":true,"isPublic":true,"latitude":0,"longitude":0,"mapCacheTime":"","mapUrlKey":"","photos":[],"place":"火车","postTime":"2014-08-27 18:46:21","remarkId":null,"replyCount":0,"sourceModel":"","sourceType":"Android客户端","timeZone":8,"eventTagsDetail":[]},{"baiduCoord":"","baikeInfo":[],"content":"现在GPS位置仍在获取，稍等","contentText":"现在GPS位置仍在获取，稍等","createTime":"2014-08-27 18:23:33","eventTags":[],"favorCount":0,"hiddenContent":"","id":7321,"isBaikeInit":true,"isCoarseCoord":true,"isPublic":true,"latitude":0,"longitude":0,"mapCacheTime":"","mapUrlKey":"","photos":[],"place":"候车室","postTime":"2014-08-27 18:23:33","remarkId":null,"replyCount":0,"sourceModel":"","sourceType":"Android客户端","timeZone":8,"eventTagsDetail":[]},{"baiduCoord":"","baikeInfo":[],"content":"我觉得随记很奇葩","contentText":"我觉得随记很奇葩","createTime":"2014-08-27 18:22:57","eventTags":[],"favorCount":0,"hiddenContent":"","id":7320,"isBaikeInit":true,"isCoarseCoord":true,"isPublic":true,"latitude":0,"longitude":0,"mapCacheTime":"","mapUrlKey":"","photos":[],"place":"候车室","postTime":"2014-08-27 18:22:57","remarkId":null,"replyCount":0,"sourceModel":"","sourceType":"Android客户端","timeZone":8,"eventTagsDetail":[]},{"baiduCoord":"","baikeInfo":[],"content":"刚才已经洗了三遍手，换了一件衣服","contentText":"刚才已经洗了三遍手，换了一件衣服","createTime":"2014-08-27 18:22:34","eventTags":[],"favorCount":0,"hiddenContent":"","id":7319,"isBaikeInit":true,"isCoarseCoord":true,"isPublic":true,"latitude":0,"longitude":0,"mapCacheTime":"","mapUrlKey":"","photos":[],"place":"候车室","postTime":"2014-08-27 18:22:34","remarkId":null,"replyCount":0,"sourceModel":"","sourceType":"Android客户端","timeZone":8,"eventTagsDetail":[]},{"baiduCoord":"","baikeInfo":[],"content":"现在随记可以发出去了吧，刚刚重启","contentText":"现在随记可以发出去了吧，刚刚重启","createTime":"2014-08-27 18:22:02","eventTags":[],"favorCount":0,"hiddenContent":"","id":7318,"isBaikeInit":true,"isCoarseCoord":true,"isPublic":true,"latitude":0,"longitude":0,"mapCacheTime":"","mapUrlKey":"","photos":[],"place":"候车室","postTime":"2014-08-27 18:22:02","remarkId":null,"replyCount":0,"sourceModel":"","sourceType":"Android客户端","timeZone":8,"eventTagsDetail":[]},{"baiduCoord":"125.33029924464712,43.91659040826763","baikeInfo":[],"content":"刚才取完票，打开妈妈买的百事可乐，居然被喷了一身……","contentText":"刚才取完票，打开妈妈买的百事可乐，居然被喷了一身……","createTime":"2014-08-27 18:05:00","eventTags":[],"favorCount":0,"hiddenContent":"","id":7317,"isBaikeInit":true,"isCoarseCoord":false,"isPublic":true,"latitude":43.90844876,"longitude":125.31721142,"mapCacheTime":"2021-05-23 15:20:03","mapUrlKey":"essay/7317/2021-05-23/map-2x.png","photos":[],"place":"长春站","postTime":"2014-08-27 18:05:00","remarkId":null,"replyCount":0,"sourceModel":"","sourceType":"Android客户端","timeZone":8,"eventTagsDetail":[]},{"baiduCoord":"125.33098998730314,43.909307564319356","baikeInfo":[],"content":"正在224上，下下站就是长春站了！","contentText":"正在224上，下下站就是长春站了！","createTime":"2014-08-27 17:40:08","eventTags":[],"favorCount":0,"hiddenContent":"","id":7315,"isBaikeInit":true,"isCoarseCoord":false,"isPublic":true,"latitude":43.90117226,"longitude":125.31790358,"mapCacheTime":"2021-05-23 15:20:04","mapUrlKey":"essay/7315/2021-05-23/map-2x.png","photos":[],"place":"车上","postTime":"2014-08-27 17:40:08","remarkId":null,"replyCount":0,"sourceModel":"","sourceType":"Android客户端","timeZone":8,"eventTagsDetail":[]},{"baiduCoord":"125.33106504800926,43.90767337282982","baikeInfo":[],"content":"哈哈哈哈，刚才随记一直发不出去，我忽然想到旧手机发不出去的条件，于是重启下手机，连接网络之后再解除锁屏，于是就能发出去啦！","contentText":"哈哈哈哈，刚才随记一直发不出去，我忽然想到旧手机发不出去的条件，于是重启下手机，连接网络之后再解除锁屏，于是就能发出去啦！","createTime":"2014-08-27 17:39:40","eventTags":[],"favorCount":0,"hiddenContent":"","id":7314,"isBaikeInit":true,"isCoarseCoord":false,"isPublic":true,"latitude":43.89953841,"longitude":125.31797936,"mapCacheTime":"2021-05-23 15:20:04","mapUrlKey":"essay/7314/2021-05-23/map-2x.png","photos":[],"place":"车上","postTime":"2014-08-27 17:39:40","remarkId":null,"replyCount":0,"sourceModel":"","sourceType":"Android客户端","timeZone":8,"eventTagsDetail":[]},{"baiduCoord":"","baikeInfo":[],"content":"已经出发啦！","contentText":"已经出发啦！","createTime":"2014-08-27 17:38:26","eventTags":[],"favorCount":0,"hiddenContent":"","id":7313,"isBaikeInit":true,"isCoarseCoord":true,"isPublic":true,"latitude":0,"longitude":0,"mapCacheTime":"","mapUrlKey":"","photos":[],"place":"车上","postTime":"2014-08-27 17:38:26","remarkId":null,"replyCount":0,"sourceModel":"","sourceType":"Android客户端","timeZone":8,"eventTagsDetail":[]},{"baiduCoord":"","baikeInfo":[],"content":"我爸给我发短信让我收拾电脑了……","contentText":"我爸给我发短信让我收拾电脑了……","createTime":"2014-08-27 16:21:17","eventTags":[],"favorCount":0,"hiddenContent":"","id":7312,"isBaikeInit":true,"isCoarseCoord":true,"isPublic":true,"latitude":0,"longitude":0,"mapCacheTime":"","mapUrlKey":"","photos":[],"place":"","postTime":"2014-08-27 16:21:17","remarkId":null,"replyCount":0,"sourceModel":"","sourceType":"Android客户端","timeZone":8,"eventTagsDetail":[]},{"baiduCoord":"","baikeInfo":[{"id":119,"word":"许嵩"},{"id":3,"word":"王芳"}],"content":"给网站首页加上了背景音乐，采用的是王芳分站技术，音乐是许嵩的《有桃花》。本来想放《舞娘》的……寻思寻思算了。","contentText":"给网站首页加上了背景音乐，采用的是王芳分站技术，音乐是许嵩的《有桃花》。本来想放《舞娘》的……寻思寻思算了。","createTime":"2014-08-27 16:20:51","eventTags":[],"favorCount":0,"hiddenContent":"","id":7311,"isBaikeInit":true,"isCoarseCoord":true,"isPublic":true,"latitude":0,"longitude":0,"mapCacheTime":"","mapUrlKey":"","photos":[],"place":"","postTime":"2014-08-27 16:20:51","remarkId":null,"replyCount":0,"sourceModel":"","sourceType":"Android客户端","timeZone":8,"eventTagsDetail":[]},{"baiduCoord":"125.3129636066495,43.90103107958965","baikeInfo":[],"content":"妈妈正在给我炒土豆丝","contentText":"妈妈正在给我炒土豆丝","createTime":"2014-08-27 13:57:42","eventTags":[],"favorCount":0,"hiddenContent":"","id":7310,"isBaikeInit":true,"isCoarseCoord":false,"isPublic":true,"latitude":43.89259772,"longitude":125.30004284,"mapCacheTime":"2021-05-23 15:20:04","mapUrlKey":"essay/7310/2021-05-23/map-2x.png","photos":[],"place":"","postTime":"2014-08-27 13:57:42","remarkId":null,"replyCount":0,"sourceModel":"","sourceType":"Android客户端","timeZone":8,"eventTagsDetail":[]},{"baiduCoord":"","baikeInfo":[],"content":"把首页显示时间的程序调了调，本来如果过时间会有问题的，现在好了。。。","contentText":"把首页显示时间的程序调了调，本来如果过时间会有问题的，现在好了。。。","createTime":"2014-08-27 11:57:48","eventTags":[],"favorCount":0,"hiddenContent":"","id":7309,"isBaikeInit":true,"isCoarseCoord":true,"isPublic":true,"latitude":0,"longitude":0,"mapCacheTime":"","mapUrlKey":"","photos":[],"place":"","postTime":"2014-08-27 11:57:48","remarkId":null,"replyCount":0,"sourceModel":"","sourceType":"Android客户端","timeZone":8,"eventTagsDetail":[]},{"baiduCoord":"125.31784453697954,43.90131777776374","baikeInfo":[],"content":"随记刚才连接失败发不出去，现在到家了","contentText":"随记刚才连接失败发不出去，现在到家了","createTime":"2014-08-27 10:44:01","eventTags":[],"favorCount":0,"hiddenContent":"","id":7308,"isBaikeInit":true,"isCoarseCoord":false,"isPublic":true,"latitude":43.89297162,"longitude":125.30487831,"mapCacheTime":"2021-05-23 15:20:05","mapUrlKey":"essay/7308/2021-05-23/map-2x.png","photos":[],"place":"","postTime":"2014-08-27 10:44:01","remarkId":null,"replyCount":0,"sourceModel":"","sourceType":"Android客户端","timeZone":8,"eventTagsDetail":[]},{"baiduCoord":"","baikeInfo":[],"content":"目前在亚泰富苑溜达","contentText":"目前在亚泰富苑溜达","createTime":"2014-08-27 09:35:34","eventTags":[],"favorCount":0,"hiddenContent":"","id":7307,"isBaikeInit":true,"isCoarseCoord":true,"isPublic":true,"latitude":0,"longitude":0,"mapCacheTime":"","mapUrlKey":"","photos":[],"place":"亚泰富苑","postTime":"2014-08-27 09:35:34","remarkId":null,"replyCount":0,"sourceModel":"","sourceType":"Android客户端","timeZone":8,"eventTagsDetail":[]},{"baiduCoord":"","baikeInfo":[],"content":"刚刚再收拾一些东西，待会出去照相之类的……","contentText":"刚刚再收拾一些东西，待会出去照相之类的……","createTime":"2014-08-27 08:04:31","eventTags":[],"favorCount":0,"hiddenContent":"","id":7306,"isBaikeInit":true,"isCoarseCoord":true,"isPublic":true,"latitude":0,"longitude":0,"mapCacheTime":"","mapUrlKey":"","photos":[],"place":"","postTime":"2014-08-27 08:04:31","remarkId":null,"replyCount":0,"sourceModel":"","sourceType":"Android客户端","timeZone":8,"eventTagsDetail":[]},{"baiduCoord":"125.31788389333614,43.90140843675492","baikeInfo":[],"content":"最后10%的电怎么也用不完，算了……","contentText":"最后10%的电怎么也用不完，算了……","createTime":"2014-08-27 00:19:15","eventTags":[],"favorCount":0,"hiddenContent":"","id":7305,"isBaikeInit":true,"isCoarseCoord":false,"isPublic":true,"latitude":43.89306314,"longitude":125.30491722,"mapCacheTime":"2021-05-23 15:20:05","mapUrlKey":"essay/7305/2021-05-23/map-2x.png","photos":[],"place":"","postTime":"2014-08-27 00:19:15","remarkId":null,"replyCount":0,"sourceModel":"","sourceType":"Android客户端","timeZone":8,"eventTagsDetail":[]}],"total":37}}